jetfuel
