Metadata-Version: 2.1
Name: jetfuel
Version: 0.0.15
Summary: Python Performance Profiling for Production
Home-page: https://github.com/jetfuel-dev/jetfuel
Author: Jared Zhao
License: Apache 2.0
Platform: UNKNOWN
Requires-Python: >=3.6
License-File: LICENSE
